{"location":{"name":"Moscow","region":"Moscow City","country":"Russia","lat":55.75,"lon":37.62,"tz_id":"Europe/Moscow","localtime_epoch":1538138093,"localtime":"2018-09-28 15:34"},"current":{"last_updated_epoch":1538137811,"last_updated":"2018-09-28 15:30","temp_c":13.0,"temp_f":55.4,"is_day":1,"condition":{"text":"Light rain","icon":"//cdn.apixu.com/weather/64x64/day/296.png","code":1183},"wind_mph":19.2,"wind_kph":31.0,"wind_degree":210,"wind_dir":"SSW","pressure_mb":997.0,"pressure_in":29.9,"precip_mm":1.1,"precip_in":0.04,"humidity":94,"cloud":50,"feelslike_c":10.4,"feelslike_f":50.8,"vis_km":9.0,"vis_miles":5.0}}